mcp_jira/__init__.py
mcp_jira/config.py
mcp_jira/logging_config.py
mcp_jira/client/__init__.py
mcp_jira/client/app.py
mcp_jira/converters/__init__.py
mcp_jira/converters/markdown_to_adf.py
mcp_jira/server/__init__.py
mcp_jira/server/app.py
mcp_jira/services/__init__.py
mcp_jira/services/jira_service.py
mcp_jira/tools/__init__.py
mcp_jira/tools/echo.py
mcp_jira/tools/jira_tools.py
mcp_jira/ui/__init__.py
mcp_jira/ui/app.py
mcp_jira/ui/components.py
mcp_jira/ui/config_io.py
mcp_jira/ui/state_manager.py
ctf_mcp_jira-0.1.5.dist-info/METADATA
ctf_mcp_jira-0.1.5.dist-info/WHEEL
ctf_mcp_jira-0.1.5.dist-info/entry_points.txt
ctf_mcp_jira-0.1.5.dist-info/top_level.txt
ctf_mcp_jira-0.1.5.dist-info/RECORD
