Metadata-Version: 2.4
Name: ctf-mcp-jira
Version: 0.1.5
Summary: MCP server for JIRA integration
Author-email: Tim Kitchens <timkitch@codingthefuture.ai>
License: MIT
Requires-Python: <3.13,>=3.11
Requires-Dist: mcp[cli]>=1.0.0
Requires-Dist: anyio>=4.0.0
Requires-Dist: starlette>=0.36.0
Requires-Dist: uvicorn>=0.27.0
Requires-Dist: PyYAML>=6.0.1
Requires-Dist: platformdirs>=4.2.2
Requires-Dist: markdown-it-py>=3.0.0
Requires-Dist: mdurl>=0.1.2
Requires-Dist: streamlit
Requires-Dist: requests>=2.31.0
